Workbook

Sheet Assumptions
A1: Iron Ledger - Financial Model
A2: Adjust blue values to run scenarios. All formulas update automatically.
A4: PRICING ASSUMPTIONS
A5: Assumption | B5: Value | C5: Unit | D5: Notes
A6: Pro Monthly Price | B6: 4.99 | C6: $/mo | D6: Current App Store price point
A7: Pro Annual Price | B7: 34.99 | C7: $/yr | D7: 42% discount vs monthly
A8: Annual vs Monthly Split | B8: 0.7 | C8: % | D8: Target: 70%+ annual subscribers
A9: Monthly Churn (Monthly Plans) | B9: 0.08 | C9: % | D9: Industry avg for utility apps
A10: Monthly Churn (Annual Plans) | B10: 0.03 | C10: % | D10: Lower due to annual commitment
A11: Free-to-Pro Conversion Rate | B11: 0.06 | C11: % | D11: Target: 5-8%; adjust if below 4%
A12: Free Tier Firearm Limit | B12: 5 | C12: firearms | D12: Primary conversion lever
A14: DERIVED METRICS
A15: Blended Monthly ARPU (Pro) | B15: =(B8*(B7/12))+((1-B8)*B6) -> 3.5380833 | D15: Weighted avg of annual and monthly subscribers
A16: Blended Monthly Churn | B16: =(B8*B10)+((1-B8)*B9) -> 0.045
A17: Avg Subscriber Lifetime (months) | B17: =IF(B16>0,1/B16,0) -> 22.222222
A18: Lifetime Value (LTV) per Pro Sub | B18: =B15*B17 -> 78.624074
A20: MONTHLY COST STRUCTURE
A21: Expense | B21: Monthly ($) | C21: Annual ($) | D21: Notes
A22: Apple Developer Program | B22: 8.33 | C22: =B22*12 -> 99.96 | D22: Required for App Store
A23: Google Play Developer (amortized) | B23: 2.08 | C23: =B23*12 -> 24.96 | D23: One-time $25 fee
A24: Paid Advertising | B24: 600 | C24: =B24*12 -> 7200 | D24: $15-25/day starting month 2
A25: Landing Page Hosting | B25: 10 | C25: =B25*12 -> 120 | D25: Vercel / Netlify
A26: Domain Name | B26: 1.5 | C26: =B26*12 -> 18 | D26: ironledgerapp.com
A27: YouTube API | B27: 0 | C27: =B27*12 -> 0 | D27: Free tier sufficient
A28: OpenAI Vision API (optional) | B28: 12 | C28: =B28*12 -> 144 | D28: Cloud AI recognition if enabled
A29: Community Backend (v2) | B29: 15 | C29: =B29*12 -> 180 | D29: Form 4 wait time aggregation
A30: Total Monthly Overhead | B30: =SUM(B22:B29) -> 648.91 | C30: =SUM(C22:C29) -> 7786.92
A32: FOUNDERS TIER
A33: Founders Lifetime Price | B33: 79.99 | C33: $ once | D33: Limited to first 500 customers
A34: Founders Purchases per Month (avg) | B34: 15 | C34: units/mo | D34: Decreases over time; front-loaded
A35: Founders Cap | B35: 500 | C35: units | D35: Raise to $99.99 after cap reached
A37: Founders Monthly Revenue | B37: =B33*B34 -> 1199.85
A38: Months Until Cap | B38: =B35/B34 -> 33.333333

Sheet Founders
A1: Iron Ledger - Founders Lifetime Tier Model
A3: Month | B3: 1 | C3: 2 | D3: 3 | E3: 4 | F3: 5 | G3: 6 | H3: 7 | I3: 8 | J3: 9 | K3: 10 | L3: 11 | M3: 12
A4: New Founders Purchases | B4: 30 | C4: 25 | D4: 25 | E4: 20 | F4: 20 | G4: 20 | H4: 15 | I4: 15 | J4: 15 | K4: 10 | L4: 10 | M4: 10
A5: Cumulative Founders | B5: =B4 -> 30 | C5: =B5+C4 -> 55 | D5: =C5+D4 -> 80 | E5: =D5+E4 -> 100 | F5: =E5+F4 -> 120 | G5: =F5+G4 -> 140 | H5: =G5+H4 -> 155 | I5: =H5+I4 -> 170 | J5: =I5+J4 -> 185 | ... M5: =L5+M4 -> 215
A6: Cap Remaining | B6: =Assumptions!$B$35-B5 -> 470 | C6: =Assumptions!$B$35-C5 -> 445 | D6: =Assumptions!$B$35-D5 -> 420 | E6: =Assumptions!$B$35-E5 -> 400 | F6: =Assumptions!$B$35-F5 -> 380 | G6: =Assumptions!$B$35-G5 -> 360 | H6: =Assumptions!$B$35-H5 -> 345 | I6: =Assumptions!$B$35-I5 -> 330 | ... M6: =Assumptions!$B$35-M5 -> 285
A7: Monthly Revenue | B7: =B4*Assumptions!$B$33 -> 2399.7 | C7: =C4*Assumptions!$B$33 -> 1999.75 | D7: =D4*Assumptions!$B$33 -> 1999.75 | E7: =E4*Assumptions!$B$33 -> 1599.8 | F7: =F4*Assumptions!$B$33 -> 1599.8 | G7: =G4*Assumptions!$B$33 -> 1599.8 | H7: =H4*Assumptions!$B$33 -> 1199.85 | I7: =I4*Assumptions!$B$33 -> 1199.85 | ... M7: =M4*Assumptions!$B$33 -> 799.9
A8: Cumulative Revenue | B8: =B7 -> 2399.7 | C8: =B8+C7 -> 4399.45 | D8: =C8+D7 -> 6399.2 | E8: =D8+E7 -> 7999 | F8: =E8+F7 -> 9598.8 | G8: =F8+G7 -> 11198.6 | H8: =G8+H7 -> 12398.45 | I8: =H8+I7 -> 13598.3 | J8: =I8+J7 -> 14798.15 | ... M8: =L8+M7 -> 17197.85
A11: SUMMARY
A12: Total Founders Sold (Yr 1) | B12: =SUM(B4:M4) -> 215
A13: Total Founders Revenue | B13: =SUM(B7:M7) -> 17197.85
A14: Avg Monthly Founders Rev | B14: =B13/12 -> 1433.1542
A15: Cap Reached Month | B15: Review when cumulative approaches 500

Sheet Conservative
A1: Iron Ledger - Conservative Projections
A2: All revenue formulas reference Assumptions sheet. Change inputs there to update.
A4: INSTALL SCHEDULE
A5: Month | B5: 1 | C5: 2 | D5: 3 | E5: 4 | F5: 5 | G5: 6 | H5: 7 | I5: 8 | J5: 9 | K5: 10 | L5: 11 | M5: 12
A6: New Installs | B6: 400 | C6: 500 | D6: 650 | E6: 700 | F6: 750 | G6: 800 | H6: 900 | I6: 1000 | J6: 1100 | K6: 1200 | L6: 1300 | M6: 1400
A7: New Pro | B7: =ROUND(B6*Assumptions!$B$11,0) -> 24 | C7: =ROUND(C6*Assumptions!$B$11,0) -> 30 | D7: =ROUND(D6*Assumptions!$B$11,0) -> 39 | E7: =ROUND(E6*Assumptions!$B$11,0) -> 42 | F7: =ROUND(F6*Assumptions!$B$11,0) -> 45 | G7: =ROUND(G6*Assumptions!$B$11,0) -> 48 | H7: =ROUND(H6*Assumptions!$B$11,0) -> 54 | I7: =ROUND(I6*Assumptions!$B$11,0) -> 60 | ... M7: =ROUND(M6*Assumptions!$B$11,0) -> 84
A8: Churned Pro | B8: 0 | C8: =ROUND(B9*Assumptions!$B$16,0) -> 1 | D8: =ROUND(C9*Assumptions!$B$16,0) -> 2 | E8: =ROUND(D9*Assumptions!$B$16,0) -> 4 | F8: =ROUND(E9*Assumptions!$B$16,0) -> 6 | G8: =ROUND(F9*Assumptions!$B$16,0) -> 8 | H8: =ROUND(G9*Assumptions!$B$16,0) -> 9 | I8: =ROUND(H9*Assumptions!$B$16,0) -> 11 | J8: =ROUND(I9*Assumptions!$B$16,0) -> 14 | ... M8: =ROUND(L9*Assumptions!$B$16,0) -> 21
A9: Active Pro | B9: =B7 -> 24 | C9: =B9+C7-C8 -> 53 | D9: =C9+D7-D8 -> 90 | E9: =D9+E7-E8 -> 128 | F9: =E9+F7-F8 -> 167 | G9: =F9+G7-G8 -> 207 | H9: =G9+H7-H8 -> 252 | I9: =H9+I7-I8 -> 301 | J9: =I9+J7-J8 -> 353 | ... M9: =L9+M7-M8 -> 532
A10: Cumul Free | B10: =B6-B7 -> 376 | C10: =B10+C6-C7 -> 846 | D10: =C10+D6-D7 -> 1457 | E10: =D10+E6-E7 -> 2115 | F10: =E10+F6-F7 -> 2820 | G10: =F10+G6-G7 -> 3572 | H10: =G10+H6-H7 -> 4418 | I10: =H10+I6-I7 -> 5358 | J10: =I10+J6-J7 -> 6392 | ... M10: =L10+M6-M7 -> 10058
A12: REVENUE
A13: Month | B13: 1 | C13: 2 | D13: 3 | E13: 4 | F13: 5 | G13: 6 | H13: 7 | I13: 8 | J13: 9 | K13: 10 | L13: 11 | M13: 12
A14: Monthly Rev | B14: =B15+B9*Assumptions!$B$15 -> 2484.614 | C14: =C15+C9*Assumptions!$B$15 -> 2187.2684 | D14: =D15+D9*Assumptions!$B$15 -> 2318.1775 | E14: =E15+E9*Assumptions!$B$15 -> 2052.6747 | F14: =F15+F9*Assumptions!$B$15 -> 2190.6599 | G14: =G15+G9*Assumptions!$B$15 -> 2332.1833 | H14: =H15+H9*Assumptions!$B$15 -> 2091.447 | I14: =I15+I9*Assumptions!$B$15 -> 2264.8131 | ... M14: =M15+M9*Assumptions!$B$15 -> 2682.1603
A15: Founders Rev | B15: =Founders!B7 -> 2399.7 | C15: =Founders!C7 -> 1999.75 | D15: =Founders!D7 -> 1999.75 | E15: =Founders!E7 -> 1599.8 | F15: =Founders!F7 -> 1599.8 | G15: =Founders!G7 -> 1599.8 | H15: =Founders!H7 -> 1199.85 | I15: =Founders!I7 -> 1199.85 | ... M15: =Founders!M7 -> 799.9
A16: Cumul Rev | B16: =B14 -> 2484.614 | C16: =B16+C14 -> 4671.8824 | D16: =C16+D14 -> 6990.0599 | E16: =D16+E14 -> 9042.7346 | F16: =E16+F14 -> 11233.395 | G16: =F16+G14 -> 13565.578 | H16: =G16+H14 -> 15657.025 | I16: =H16+I14 -> 17921.838 | J16: =I16+J14 -> 20370.631 | ... M16: =L16+M14 -> 27759.029
A17: Monthly Cost | B17: =Assumptions!$B$30 -> 648.91 | C17: =Assumptions!$B$30 -> 648.91 | D17: =Assumptions!$B$30 -> 648.91 | E17: =Assumptions!$B$30 -> 648.91 | F17: =Assumptions!$B$30 -> 648.91 | G17: =Assumptions!$B$30 -> 648.91 | H17: =Assumptions!$B$30 -> 648.91 | I17: =Assumptions!$B$30 -> 648.91 | ... M17: =Assumptions!$B$30 -> 648.91
A18: Monthly P/L | B18: =B14-B16 -> 0 | C18: =C14-C16 -> -2484.614 | D18: =D14-D16 -> -4671.8824 | E18: =E14-E16 -> -6990.0599 | F18: =F14-F16 -> -9042.7346 | G18: =G14-G16 -> -11233.395 | H18: =H14-H16 -> -13565.578 | I18: =I14-I16 -> -15657.025 | ... M18: =M14-M16 -> -25076.868
A19: Cumul P/L | B19: =B17 -> 648.91 | C19: =B18+C17 -> 648.91 | D19: =C18+D17 -> -1835.704 | E19: =D18+E17 -> -4022.9724 | F19: =E18+F17 -> -6341.1499 | G19: =F18+G17 -> -8393.8246 | H19: =G18+H17 -> -10584.485 | I19: =H18+I17 -> -12916.668 | J19: =I18+J17 -> -15008.115 | ... M19: =L18+M17 -> -21968.697
A21: KEY METRICS
A22: Total Installs (Yr1) | B22: =SUM(B6:M6) -> 10700
A23: Active Pro (Yr End) | B23: =M9 -> 532
A24: Year 1 Revenue | B24: =M15 -> 799.9
A25: Year 1 Costs | B25: =SUM(B16:M16) -> 177391.26
A26: Year 1 Profit/Loss | B26: =B23-B24 -> -267.9
A27: ARR (Month 12) | B27: =M14*12 -> 32185.924
A28: LTV:CAC Ratio | B28: See Assumptions tab

Sheet Moderate
A1: Iron Ledger - Moderate Projections
A2: All revenue formulas reference Assumptions sheet. Change inputs there to update.
A4: INSTALL SCHEDULE
A5: Month | B5: 1 | C5: 2 | D5: 3 | E5: 4 | F5: 5 | G5: 6 | H5: 7 | I5: 8 | J5: 9 | K5: 10 | L5: 11 | M5: 12
A6: New Installs | B6: 600 | C6: 800 | D6: 1100 | E6: 1300 | F6: 1500 | G6: 1800 | H6: 2000 | I6: 2200 | J6: 2500 | K6: 2800 | L6: 3000 | M6: 3200
A7: New Pro | B7: =ROUND(B6*Assumptions!$B$11,0) -> 36 | C7: =ROUND(C6*Assumptions!$B$11,0) -> 48 | D7: =ROUND(D6*Assumptions!$B$11,0) -> 66 | E7: =ROUND(E6*Assumptions!$B$11,0) -> 78 | F7: =ROUND(F6*Assumptions!$B$11,0) -> 90 | G7: =ROUND(G6*Assumptions!$B$11,0) -> 108 | H7: =ROUND(H6*Assumptions!$B$11,0) -> 120 | I7: =ROUND(I6*Assumptions!$B$11,0) -> 132 | ... M7: =ROUND(M6*Assumptions!$B$11,0) -> 192
A8: Churned Pro | B8: 0 | C8: =ROUND(B9*Assumptions!$B$16,0) -> 2 | D8: =ROUND(C9*Assumptions!$B$16,0) -> 4 | E8: =ROUND(D9*Assumptions!$B$16,0) -> 6 | F8: =ROUND(E9*Assumptions!$B$16,0) -> 10 | G8: =ROUND(F9*Assumptions!$B$16,0) -> 13 | H8: =ROUND(G9*Assumptions!$B$16,0) -> 18 | I8: =ROUND(H9*Assumptions!$B$16,0) -> 22 | J8: =ROUND(I9*Assumptions!$B$16,0) -> 27 | ... M8: =ROUND(L9*Assumptions!$B$16,0) -> 45
A9: Active Pro | B9: =B7 -> 36 | C9: =B9+C7-C8 -> 82 | D9: =C9+D7-D8 -> 144 | E9: =D9+E7-E8 -> 216 | F9: =E9+F7-F8 -> 296 | G9: =F9+G7-G8 -> 391 | H9: =G9+H7-H8 -> 493 | I9: =H9+I7-I8 -> 603 | J9: =I9+J7-J8 -> 726 | ... M9: =L9+M7-M8 -> 1149
A10: Cumul Free | B10: =B6-B7 -> 564 | C10: =B10+C6-C7 -> 1316 | D10: =C10+D6-D7 -> 2350 | E10: =D10+E6-E7 -> 3572 | F10: =E10+F6-F7 -> 4982 | G10: =F10+G6-G7 -> 6674 | H10: =G10+H6-H7 -> 8554 | I10: =H10+I6-I7 -> 10622 | J10: =I10+J6-J7 -> 12972 | ... M10: =L10+M6-M7 -> 21432
A12: REVENUE
A13: Month | B13: 1 | C13: 2 | D13: 3 | E13: 4 | F13: 5 | G13: 6 | H13: 7 | I13: 8 | J13: 9 | K13: 10 | L13: 11 | M13: 12
A14: Monthly Rev | B14: =B15+B9*Assumptions!$B$15 -> 2527.071 | C14: =C15+C9*Assumptions!$B$15 -> 2289.8728 | D14: =D15+D9*Assumptions!$B$15 -> 2509.234 | E14: =E15+E9*Assumptions!$B$15 -> 2364.026 | F14: =F15+F9*Assumptions!$B$15 -> 2647.0727 | G14: =G15+G9*Assumptions!$B$15 -> 2983.1906 | H14: =H15+H9*Assumptions!$B$15 -> 2944.1251 | I14: =I15+I9*Assumptions!$B$15 -> 3333.3142 | ... M14: =M15+M9*Assumptions!$B$15 -> 4865.1578
A15: Founders Rev | B15: =Founders!B7 -> 2399.7 | C15: =Founders!C7 -> 1999.75 | D15: =Founders!D7 -> 1999.75 | E15: =Founders!E7 -> 1599.8 | F15: =Founders!F7 -> 1599.8 | G15: =Founders!G7 -> 1599.8 | H15: =Founders!H7 -> 1199.85 | I15: =Founders!I7 -> 1199.85 | ... M15: =Founders!M7 -> 799.9
A16: Cumul Rev | B16: =B14 -> 2527.071 | C16: =B16+C14 -> 4816.9438 | D16: =C16+D14 -> 7326.1778 | E16: =D16+E14 -> 9690.2038 | F16: =E16+F14 -> 12337.276 | G16: =F16+G14 -> 15320.467 | H16: =G16+H14 -> 18264.592 | I16: =H16+I14 -> 21597.906 | J16: =I16+J14 -> 25366.405 | ... M16: =L16+M14 -> 38422.812
A17: Monthly Cost | B17: =Assumptions!$B$30 -> 648.91 | C17: =Assumptions!$B$30 -> 648.91 | D17: =Assumptions!$B$30 -> 648.91 | E17: =Assumptions!$B$30 -> 648.91 | F17: =Assumptions!$B$30 -> 648.91 | G17: =Assumptions!$B$30 -> 648.91 | H17: =Assumptions!$B$30 -> 648.91 | I17: =Assumptions!$B$30 -> 648.91 | ... M17: =Assumptions!$B$30 -> 648.91
A18: Monthly P/L | B18: =B14-B16 -> 0 | C18: =C14-C16 -> -2527.071 | D18: =D14-D16 -> -4816.9438 | E18: =E14-E16 -> -7326.1778 | F18: =F14-F16 -> -9690.2038 | G18: =G14-G16 -> -12337.276 | H18: =H14-H16 -> -15320.467 | I18: =I14-I16 -> -18264.592 | ... M18: =M14-M16 -> -33557.654
A19: Cumul P/L | B19: =B17 -> 648.91 | C19: =B18+C17 -> 648.91 | D19: =C18+D17 -> -1878.161 | E19: =D18+E17 -> -4168.0338 | F19: =E18+F17 -> -6677.2678 | G19: =F18+G17 -> -9041.2938 | H19: =G18+H17 -> -11688.367 | I19: =H18+I17 -> -14671.557 | J19: =I18+J17 -> -17615.682 | ... M19: =L18+M17 -> -28563.685
A21: KEY METRICS
A22: Total Installs (Yr1) | B22: =SUM(B6:M6) -> 22800
A23: Active Pro (Yr End) | B23: =M9 -> 1149
A24: Year 1 Revenue | B24: =M15 -> 799.9
A25: Year 1 Costs | B25: =SUM(B16:M16) -> 218440.1
A26: Year 1 Profit/Loss | B26: =B23-B24 -> 349.1
A27: ARR (Month 12) | B27: =M14*12 -> 58381.893
A28: LTV:CAC Ratio | B28: See Assumptions tab

Sheet Optimistic
A1: Iron Ledger - Optimistic Projections
A2: All revenue formulas reference Assumptions sheet. Change inputs there to update.
A4: INSTALL SCHEDULE
A5: Month | B5: 1 | C5: 2 | D5: 3 | E5: 4 | F5: 5 | G5: 6 | H5: 7 | I5: 8 | J5: 9 | K5: 10 | L5: 11 | M5: 12
A6: New Installs | B6: 1000 | C6: 1500 | D6: 2500 | E6: 3500 | F6: 4000 | G6: 4500 | H6: 5000 | I6: 5500 | J6: 6000 | K6: 6500 | L6: 7000 | M6: 7500
A7: New Pro | B7: =ROUND(B6*Assumptions!$B$11,0) -> 60 | C7: =ROUND(C6*Assumptions!$B$11,0) -> 90 | D7: =ROUND(D6*Assumptions!$B$11,0) -> 150 | E7: =ROUND(E6*Assumptions!$B$11,0) -> 210 | F7: =ROUND(F6*Assumptions!$B$11,0) -> 240 | G7: =ROUND(G6*Assumptions!$B$11,0) -> 270 | H7: =ROUND(H6*Assumptions!$B$11,0) -> 300 | I7: =ROUND(I6*Assumptions!$B$11,0) -> 330 | ... M7: =ROUND(M6*Assumptions!$B$11,0) -> 450
A8: Churned Pro | B8: 0 | C8: =ROUND(B9*Assumptions!$B$16,0) -> 3 | D8: =ROUND(C9*Assumptions!$B$16,0) -> 7 | E8: =ROUND(D9*Assumptions!$B$16,0) -> 13 | F8: =ROUND(E9*Assumptions!$B$16,0) -> 22 | G8: =ROUND(F9*Assumptions!$B$16,0) -> 32 | H8: =ROUND(G9*Assumptions!$B$16,0) -> 42 | I8: =ROUND(H9*Assumptions!$B$16,0) -> 54 | J8: =ROUND(I9*Assumptions!$B$16,0) -> 66 | ... M8: =ROUND(L9*Assumptions!$B$16,0) -> 108
A9: Active Pro | B9: =B7 -> 60 | C9: =B9+C7-C8 -> 147 | D9: =C9+D7-D8 -> 290 | E9: =D9+E7-E8 -> 487 | F9: =E9+F7-F8 -> 705 | G9: =F9+G7-G8 -> 943 | H9: =G9+H7-H8 -> 1201 | I9: =H9+I7-I8 -> 1477 | J9: =I9+J7-J8 -> 1771 | ... M9: =L9+M7-M8 -> 2749
A10: Cumul Free | B10: =B6-B7 -> 940 | C10: =B10+C6-C7 -> 2350 | D10: =C10+D6-D7 -> 4700 | E10: =D10+E6-E7 -> 7990 | F10: =E10+F6-F7 -> 11750 | G10: =F10+G6-G7 -> 15980 | H10: =G10+H6-H7 -> 20680 | I10: =H10+I6-I7 -> 25850 | J10: =I10+J6-J7 -> 31490 | ... M10: =L10+M6-M7 -> 51230
A12: REVENUE
A13: Month | B13: 1 | C13: 2 | D13: 3 | E13: 4 | F13: 5 | G13: 6 | H13: 7 | I13: 8 | J13: 9 | K13: 10 | L13: 11 | M13: 12
A14: Monthly Rev | B14: =B15+B9*Assumptions!$B$15 -> 2611.985 | C14: =C15+C9*Assumptions!$B$15 -> 2519.8483 | D14: =D15+D9*Assumptions!$B$15 -> 3025.7942 | E14: =E15+E9*Assumptions!$B$15 -> 3322.8466 | F14: =F15+F9*Assumptions!$B$15 -> 4094.1487 | G14: =G15+G9*Assumptions!$B$15 -> 4936.2126 | H14: =H15+H9*Assumptions!$B$15 -> 5449.0881 | I14: =I15+I9*Assumptions!$B$15 -> 6425.5991 | ... M14: =M15+M9*Assumptions!$B$15 -> 10526.091
A15: Founders Rev | B15: =Founders!B7 -> 2399.7 | C15: =Founders!C7 -> 1999.75 | D15: =Founders!D7 -> 1999.75 | E15: =Founders!E7 -> 1599.8 | F15: =Founders!F7 -> 1599.8 | G15: =Founders!G7 -> 1599.8 | H15: =Founders!H7 -> 1199.85 | I15: =Founders!I7 -> 1199.85 | ... M15: =Founders!M7 -> 799.9
A16: Cumul Rev | B16: =B14 -> 2611.985 | C16: =B16+C14 -> 5131.8332 | D16: =C16+D14 -> 8157.6274 | E16: =D16+E14 -> 11480.474 | F16: =E16+F14 -> 15574.623 | G16: =F16+G14 -> 20510.835 | H16: =G16+H14 -> 25959.923 | I16: =H16+I14 -> 32385.522 | J16: =I16+J14 -> 39851.318 | ... M16: =L16+M14 -> 67856.127
A17: Monthly Cost | B17: =Assumptions!$B$30 -> 648.91 | C17: =Assumptions!$B$30 -> 648.91 | D17: =Assumptions!$B$30 -> 648.91 | E17: =Assumptions!$B$30 -> 648.91 | F17: =Assumptions!$B$30 -> 648.91 | G17: =Assumptions!$B$30 -> 648.91 | H17: =Assumptions!$B$30 -> 648.91 | I17: =Assumptions!$B$30 -> 648.91 | ... M17: =Assumptions!$B$30 -> 648.91
A18: Monthly P/L | B18: =B14-B16 -> 0 | C18: =C14-C16 -> -2611.985 | D18: =D14-D16 -> -5131.8332 | E18: =E14-E16 -> -8157.6274 | F18: =F14-F16 -> -11480.474 | G18: =G14-G16 -> -15574.623 | H18: =H14-H16 -> -20510.835 | I18: =I14-I16 -> -25959.923 | ... M18: =M14-M16 -> -57330.036
A19: Cumul P/L | B19: =B17 -> 648.91 | C19: =B18+C17 -> 648.91 | D19: =C18+D17 -> -1963.075 | E19: =D18+E17 -> -4482.9232 | F19: =E18+F17 -> -7508.7174 | G19: =F18+G17 -> -10831.564 | H19: =G18+H17 -> -14925.713 | I19: =H18+I17 -> -19861.925 | J19: =I18+J17 -> -25311.013 | ... M19: =L18+M17 -> -47365.06
A21: KEY METRICS
A22: Total Installs (Yr1) | B22: =SUM(B6:M6) -> 54500
A23: Active Pro (Yr End) | B23: =M9 -> 2749
A24: Year 1 Revenue | B24: =M15 -> 799.9
A25: Year 1 Costs | B25: =SUM(B16:M16) -> 334864.27
A26: Year 1 Profit/Loss | B26: =B23-B24 -> 1949.1
A27: ARR (Month 12) | B27: =M14*12 -> 126313.09
A28: LTV:CAC Ratio | B28: See Assumptions tab

Sheet Combined Summary
A1: Iron Ledger - Combined Year 1 Summary
A3: Metric | B3: Conservative + Founders | C3: Moderate + Founders | D3: Optimistic + Founders
A4: Subscription Revenue | B4: =Conservative!M16 -> 27759.029 | C4: =Moderate!M16 -> 38422.812 | D4: =Optimistic!M16 -> 67856.127
A5: Founders Revenue | B5: =Founders!B13 -> 17197.85 | C5: =Founders!B13 -> 17197.85 | D5: =Founders!B13 -> 17197.85
A6: Total Revenue | B6: =B4+B5 -> 44956.879 | C6: =C4+C5 -> 55620.662 | D6: =D4+D5 -> 85053.977
A8: Total Costs | B8: =Conservative!B25 -> 177391.26 | C8: =Moderate!B25 -> 218440.1 | D8: =Optimistic!B25 -> 334864.27
A9: Net Profit/Loss | B9: =B6-B8 -> -132434.38 | C9: =C6-C8 -> -162819.44 | D9: =D6-D8 -> -249810.3

Sheet Comparison
A1: Scenario Comparison - Year 1 Summary
A3: Metric | B3: Conservative | C3: Moderate | D3: Optimistic
A4: Total Installs | B4: =Conservative!B21 -> 0 | C4: =Moderate!B21 -> 0 | D4: =Optimistic!B21 -> 0
A5: Active Pro Subs (Yr End) | B5: =Conservative!B22 -> 10700 | C5: =Moderate!B22 -> 22800 | D5: =Optimistic!B22 -> 54500
A6: Year 1 Revenue | B6: =Conservative!B23 -> 532 | C6: =Moderate!B23 -> 1149 | D6: =Optimistic!B23 -> 2749
A7: Year 1 Costs | B7: =Conservative!B24 -> 799.9 | C7: =Moderate!B24 -> 799.9 | D7: =Optimistic!B24 -> 799.9
A8: Year 1 Profit/Loss | B8: =Conservative!B25 -> 177391.26 | C8: =Moderate!B25 -> 218440.1 | D8: =Optimistic!B25 -> 334864.27
A9: ARR (Month 12) | B9: =Conservative!B26 -> -267.9 | C9: =Moderate!B26 -> 349.1 | D9: =Optimistic!B26 -> 1949.1
A10: Pro LTV | B10: =Assumptions!B18 -> 78.624074 | C10: =Assumptions!B18 -> 78.624074 | D10: =Assumptions!B18 -> 78.624074
A11: Monthly Overhead | B11: =Assumptions!B30 -> 648.91 | C11: =Assumptions!B30 -> 648.91 | D11: =Assumptions!B30 -> 648.91
A13: Break-Even Analysis
A14: Monthly break-even subs | B14: =IF(Assumptions!B15>0,CEILING(Assumptions!B30/Assumptions!B15,1),0) -> 184 | C14: Pro subscribers needed to cover monthly costs
